Metadata-Version: 2.1
Name: libpythonproSantos
Version: 0.1
Summary: Module for building Python Projects in Pytools course.
Home-page: https://github.com/ClaraSantosmf/NewClass
Author: Clara Santos
Author-email:  
License: GNU AFFERO GENERAL PUBLIC LICENSE
Platform: UNKNOWN
Classifier: Development Status :: 2 - Pre-Alpha
Classifier: Environment :: Console
Classifier: Intended Audience :: Developers
Classifier: License :: OSI Approved :: GNU Affero General Public License v3 or later (AGPLv3+)
Classifier: Operating System :: OS Independent
Classifier: Programming Language :: Python
Classifier: Programming Language :: Python :: 3.9
Classifier: Framework :: Pytest
